rq_transformer/__init__.py
rq_transformer/hierarchical_causal_transformer.py
rq_transformer/rq_transformer.py
RQ_transformer-0.1.9.dist-info/LICENSE
RQ_transformer-0.1.9.dist-info/METADATA
RQ_transformer-0.1.9.dist-info/WHEEL
RQ_transformer-0.1.9.dist-info/top_level.txt
RQ_transformer-0.1.9.dist-info/RECORD
